dataesg/__init__.py
dataesg/api_config.py
dataesg/api_init.py
dataesg/connection.py
dataesg/data.py
dataesg/database.py
dataesg/get.py
dataesg/visualizations.py
dataesg-0.0.2.dist-info/LICENSE.txt
dataesg-0.0.2.dist-info/METADATA
dataesg-0.0.2.dist-info/WHEEL
dataesg-0.0.2.dist-info/top_level.txt
dataesg-0.0.2.dist-info/RECORD
