Metadata-Version: 2.1
Name: dataesg
Version: 0.0.2
Summary: Package for dataesg data access
Home-page: https://github.com/dataesg/dataesg-python
Author: DATAESG
Author-email: hello@dataesg.com
License: MIT
Download-URL: https://github.com/dataesg/dataesg-python/archive/v_002.tar.gz
Keywords: dataesg,data,api
Platform: UNKNOWN
Classifier: Intended Audience :: Developers
Classifier: License :: OSI Approved :: MIT License
Classifier: Operating System :: OS Independent
Classifier: Programming Language :: Python :: 3
Classifier: Programming Language :: Python :: 3.5
Classifier: Programming Language :: Python :: 3.6
Classifier: Programming Language :: Python :: 3.7
Classifier: Programming Language :: Python :: 3.8
Requires-Python: >= 3.5
Requires-Dist: pandas (>=0.14)
Requires-Dist: numpy (>=1.8)
Requires-Dist: requests (>=2.7.0)
Requires-Dist: matplotlib (>=3.1.3)
